rich2md/__init__.py
rich2md-0.1.0.dist-info/WHEEL
rich2md-0.1.0.dist-info/METADATA
rich2md-0.1.0.dist-info/RECORD
