Metadata-Version: 2.1
Name: rich2md
Version: 0.1.0
Summary: Convert Rich tables to Markdown tables
License: MIT
Author: Krzysztof J. Czarnecki
Author-email: kjczarne@gmail.com
Requires-Python: >=3.10,<4.0
Classifier: License :: OSI Approved :: MIT License
Classifier: Programming Language :: Python :: 3
Classifier: Programming Language :: Python :: 3.10
Classifier: Programming Language :: Python :: 3.11
Requires-Dist: pandas (>=2.2.3,<3.0.0)
Requires-Dist: rich (>=13.9.2,<14.0.0)
